[
  {
    "cycle": 0,
    "E": 79,
    "C": 15,
    "burn": 0.32500000000000007,
    "structure_size": 8,
    "actions": [
      "B",
      "M",
      "R",
      "K"
    ]
  },
  {
    "cycle": 1,
    "E": 58,
    "C": 15,
    "burn": 0.3166666666666667,
    "structure_size": 6,
    "actions": [
      "B",
      "M",
      "R",
      "K"
    ]
  },
  {
    "cycle": 2,
    "E": 37,
    "C": 15,
    "burn": 0.3500000000000001,
    "structure_size": 3,
    "actions": [
      "B",
      "M",
      "R",
      "K"
    ]
  },
  {
    "cycle": 3,
    "E": 36,
    "C": 5,
    "burn": 0.1,
    "structure_size": 2,
    "actions": [
      "B",
      "K"
    ]
  },
  {
    "cycle": 4,
    "E": 35,
    "C": 5,
    "burn": 0.05,
    "structure_size": 0,
    "actions": [
      "B",
      "K"
    ]
  }
]